numgraph/__init__.py
numgraph/dataset.py
numgraph/graph_builder.py
numgraph/parser.py
numgraph/visualizer.py
numgraph_equation-0.1.3.dist-info/METADATA
numgraph_equation-0.1.3.dist-info/WHEEL
numgraph_equation-0.1.3.dist-info/top_level.txt
numgraph_equation-0.1.3.dist-info/RECORD
