Metadata-Version: 2.1
Name: numgraph-equation
Version: 0.1.3
Summary: Convert mathematical equations into graph structures for visualization
Author-email: Ayush Jwalaprasad Mishra <luckymishra312004@gmail.com>
Project-URL: Homepage, https://github.com/Ayush-07-Mishra/numgraph
Project-URL: Documentation, https://github.com/Ayush-07-Mishra/numgraph#readme
Project-URL: Repository, https://github.com/Ayush-07-Mishra/numgraph
Project-URL: Bug Tracker, https://github.com/Ayush-07-Mishra/numgraph/issues
Keywords: mathematics,graph,visualization,equation,sympy,networkx
Classifier: Development Status :: 3 - Alpha
Classifier: Intended Audience :: Education
Classifier: Intended Audience :: Science/Research
Classifier: Topic :: Scientific/Engineering :: Mathematics
Classifier: Topic :: Scientific/Engineering :: Visualization
Classifier: Programming Language :: Python :: 3
Classifier: Programming Language :: Python :: 3.8
Classifier: Programming Language :: Python :: 3.9
Classifier: Programming Language :: Python :: 3.10
Classifier: Programming Language :: Python :: 3.11
Classifier: Programming Language :: Python :: 3.12
Requires-Python: >=3.8
Requires-Dist: sympy>=1.12
Requires-Dist: networkx>=3.1
Requires-Dist: matplotlib>=3.7.0
Requires-Dist: pyvis>=0.3.2
Requires-Dist: numpy>=1.24.0
Provides-Extra: dev
Requires-Dist: pytest>=7.4.0; extra == "dev"
Requires-Dist: pytest-cov>=4.1.0; extra == "dev"
Requires-Dist: black>=23.0.0; extra == "dev"
Requires-Dist: flake8>=6.0.0; extra == "dev"
Requires-Dist: mypy>=1.0.0; extra == "dev"
